LICENSE
README.md
README.rst
setup.py
pyc_zipper/__init__.py
pyc_zipper/__main__.py
pyc_zipper/compress.py
pyc_zipper/obfuscate.py
pyc_zipper/unpack.py
pyc_zipper/utils.py
pyc_zipper.egg-info/PKG-INFO
pyc_zipper.egg-info/SOURCES.txt
pyc_zipper.egg-info/dependency_links.txt
pyc_zipper.egg-info/entry_points.txt
pyc_zipper.egg-info/requires.txt
pyc_zipper.egg-info/top_level.txt
pyc_zipper/tests/test_obfuscate_closure.py
pyc_zipper/tests/test_obfuscate_code_name.py
pyc_zipper/tests/test_obfuscate_super.py